{
  "snapshots": [
    {
      "date": "2026-07-08",
      "brands": {
        "primebook": {
          "subscribers": 15600,
          "total_views": 2249769,
          "video_count": 122
        },
        "hp": {
          "subscribers": 200000,
          "total_views": 1417484786,
          "video_count": 685
        },
        "lenovo": {
          "subscribers": 395000,
          "total_views": 2449013713,
          "video_count": 1197
        },
        "acer": {
          "subscribers": 39400,
          "total_views": 810579929,
          "video_count": 511
        },
        "dell": {
          "subscribers": 229000,
          "total_views": 1120233910,
          "video_count": 293
        },
        "asus": {
          "subscribers": 234000,
          "total_views": 357450857,
          "video_count": 715
        }
      }
    },
    {
      "date": "2026-07-10",
      "brands": {
        "primebook": {
          "subscribers": 15600,
          "total_views": 2252420,
          "video_count": 122
        },
        "hp": {
          "subscribers": 200000,
          "total_views": 1418332422,
          "video_count": 685
        },
        "lenovo": {
          "subscribers": 395000,
          "total_views": 2479594998,
          "video_count": 1198
        },
        "acer": {
          "subscribers": 39400,
          "total_views": 811197092,
          "video_count": 512
        },
        "dell": {
          "subscribers": 229000,
          "total_views": 1235493432,
          "video_count": 297
        },
        "asus": {
          "subscribers": 234000,
          "total_views": 357456785,
          "video_count": 718
        }
      }
    },
    {
      "date": "2026-07-11",
      "brands": {
        "primebook": {
          "subscribers": 15600,
          "total_views": 2255383,
          "video_count": 122
        },
        "hp": {
          "subscribers": 200000,
          "total_views": 1419670676,
          "video_count": 685
        },
        "lenovo": {
          "subscribers": 395000,
          "total_views": 2495980847,
          "video_count": 1198
        },
        "acer": {
          "subscribers": 39400,
          "total_views": 812596292,
          "video_count": 512
        },
        "dell": {
          "subscribers": 229000,
          "total_views": 1244352625,
          "video_count": 297
        },
        "asus": {
          "subscribers": 234000,
          "total_views": 357464302,
          "video_count": 719
        }
      }
    },
    {
      "date": "2026-07-13",
      "brands": {
        "primebook": {
          "subscribers": 15600,
          "total_views": 2258945,
          "video_count": 122
        },
        "hp": {
          "subscribers": 200000,
          "total_views": 1421815169,
          "video_count": 685
        },
        "lenovo": {
          "subscribers": 395000,
          "total_views": 2532950636,
          "video_count": 1198
        },
        "acer": {
          "subscribers": 39400,
          "total_views": 814271368,
          "video_count": 512
        },
        "dell": {
          "subscribers": 229000,
          "total_views": 1253973888,
          "video_count": 297
        },
        "asus": {
          "subscribers": 234000,
          "total_views": 357472527,
          "video_count": 720
        }
      }
    },
    {
      "date": "2026-07-14",
      "brands": {
        "primebook": {
          "subscribers": 15600,
          "total_views": 2260250,
          "video_count": 122
        },
        "hp": {
          "subscribers": 200000,
          "total_views": 1422765703,
          "video_count": 685
        },
        "lenovo": {
          "subscribers": 395000,
          "total_views": 2548427857,
          "video_count": 1206
        },
        "acer": {
          "subscribers": 39400,
          "total_views": 814988995,
          "video_count": 512
        },
        "dell": {
          "subscribers": 229000,
          "total_views": 1257884160,
          "video_count": 297
        },
        "asus": {
          "subscribers": 234000,
          "total_views": 357476618,
          "video_count": 722
        }
      }
    },
    {
      "date": "2026-07-15",
      "brands": {
        "primebook": {
          "subscribers": 15600,
          "total_views": 2260774,
          "video_count": 122
        },
        "hp": {
          "subscribers": 200000,
          "total_views": 1423941799,
          "video_count": 686
        },
        "lenovo": {
          "subscribers": 395000,
          "total_views": 2562636780,
          "video_count": 1206
        },
        "acer": {
          "subscribers": 39400,
          "total_views": 815179048,
          "video_count": 512
        },
        "dell": {
          "subscribers": 229000,
          "total_views": 1262728557,
          "video_count": 299
        },
        "asus": {
          "subscribers": 234000,
          "total_views": 357480682,
          "video_count": 723
        }
      }
    },
    {
      "date": "2026-07-19",
      "brands": {
        "primebook": {
          "subscribers": 16000,
          "total_views": 2270305,
          "video_count": 122
        },
        "hp": {
          "subscribers": 200000,
          "total_views": 1433580682,
          "video_count": 688
        },
        "lenovo": {
          "subscribers": 395000,
          "total_views": 2628701886,
          "video_count": 1209
        },
        "acer": {
          "subscribers": 39400,
          "total_views": 819687666,
          "video_count": 512
        },
        "dell": {
          "subscribers": 229000,
          "total_views": 1283148414,
          "video_count": 299
        },
        "asus": {
          "subscribers": 234000,
          "total_views": 357498513,
          "video_count": 730
        }
      }
    },
    {
      "date": "2026-07-20",
      "brands": {
        "primebook": {
          "subscribers": 16000,
          "total_views": 2271834,
          "video_count": 122
        },
        "hp": {
          "subscribers": 200000,
          "total_views": 1436213352,
          "video_count": 688
        },
        "lenovo": {
          "subscribers": 395000,
          "total_views": 2639672293,
          "video_count": 1209
        },
        "acer": {
          "subscribers": 39400,
          "total_views": 820384141,
          "video_count": 512
        },
        "dell": {
          "subscribers": 229000,
          "total_views": 1286497050,
          "video_count": 299
        },
        "asus": {
          "subscribers": 234000,
          "total_views": 357501802,
          "video_count": 730
        }
      }
    }
  ]
}